ecma426/__init__.py
ecma426/codec.py
ecma426/model.py
ecma426/scmversion.py
ecma426/tests.py
ecma426/vlq.py
ecma426/scripts/__init__.py
ecma426/scripts/identity_sourcemap.py
ecma426-0.2.0.dist-info/licenses/LICENSE
ecma426-0.2.0.dist-info/METADATA
ecma426-0.2.0.dist-info/WHEEL
ecma426-0.2.0.dist-info/entry_points.txt
ecma426-0.2.0.dist-info/top_level.txt
ecma426-0.2.0.dist-info/RECORD
