Metadata-Version: 2.4
Name: ecma426
Version: 0.2.0
Summary: Run arbirary scripts with sentry_sdk initialized to some DSN on the fly
Author-email: "Bugsink B.V." <info@bugsink.com>
License-Expression: BSD-3-Clause
Project-URL: repository, https://github.com/bugsink/ecma426/
Project-URL: issues, https://github.com/bugsink/ecma426/issues
Classifier: Programming Language :: Python :: 3
Requires-Python: >=3.10
License-File: LICENSE
Dynamic: license-file
